LICENSE
README.md
setup.py
VoxelForge/__init__.py
VoxelForge/core.py
VoxelForge/main.cpp
VoxelForge/octree.cpp
VoxelForge/utils.py
VoxelForge/voxel.cpp
VoxelForge.egg-info/PKG-INFO
VoxelForge.egg-info/SOURCES.txt
VoxelForge.egg-info/dependency_links.txt
VoxelForge.egg-info/not-zip-safe
VoxelForge.egg-info/requires.txt
VoxelForge.egg-info/top_level.txt
tests/__init__.py
tests/test_battery.py
tests/test_core.py
tests/test_speed_tensor_add.py
tests/test_voxel_id.py