Metadata-Version: 2.1
Name: VoxelForge
Version: 0.1.1
Summary: A high-performance Python package for efficient voxel and mesh model creation, with C++ backend.
Home-page: https://github.com/andrewrgarcia/VoxelForge
Author: Andrew Garcia
Author-email: garcia.gtr@gmail.com
License: BSD-3-Clause
Classifier: Development Status :: 3 - Alpha
Classifier: Intended Audience :: Developers
Classifier: Topic :: Software Development :: Build Tools
Classifier: License :: OSI Approved :: BSD License
Classifier: Programming Language :: Python :: 3
Classifier: Programming Language :: Python :: 3.7
Classifier: Programming Language :: Python :: 3.8
Classifier: Programming Language :: Python :: 3.9
Classifier: Programming Language :: C++
Classifier: Operating System :: OS Independent
Requires-Python: >=3.7
License-File: LICENSE
Requires-Dist: pybind11>=2.6.0
Requires-Dist: torch
